equal_odds/__init__.py
equal_odds/_version.py
equal_odds/classifiers.py
equal_odds/cvxpy_utils.py
equal_odds/equal_odds.py
equal_odds/roc_utils.py
equal_odds-0.0.7.dist-info/LICENSE
equal_odds-0.0.7.dist-info/METADATA
equal_odds-0.0.7.dist-info/WHEEL
equal_odds-0.0.7.dist-info/top_level.txt
equal_odds-0.0.7.dist-info/RECORD
