Metadata-Version: 2.1
Name: equal-odds
Version: 0.0.7
Summary: _PACKAGE UNDER CONSTRUCTION_
Home-page: https://github.com/AndreFCruz/equal-odds
Author: AndreFCruz
License: MIT
Keywords: ml,optimization,fairness
Classifier: Development Status :: 3 - Alpha
Classifier: License :: OSI Approved :: MIT License
Classifier: Intended Audience :: Science/Research
Classifier: Topic :: Scientific/Engineering :: Artificial Intelligence
Classifier: Natural Language :: English
Classifier: Programming Language :: Python :: 3
Classifier: Programming Language :: Python :: 3.8
Classifier: Programming Language :: Python :: 3.9
Classifier: Programming Language :: Python :: 3.10
Classifier: Programming Language :: Python :: 3.11
Requires-Python: >=3.8
License-File: LICENSE
Requires-Dist: pandas
Requires-Dist: numpy
Requires-Dist: scipy
Requires-Dist: scikit-learn
Requires-Dist: cvxpy
Requires-Dist: matplotlib
Requires-Dist: seaborn
Provides-Extra: dev
Requires-Dist: pytest ; extra == 'dev'
Requires-Dist: folktables ; extra == 'dev'
Requires-Dist: tqdm ; extra == 'dev'
Provides-Extra: test
Requires-Dist: ipdb ; extra == 'test'
Requires-Dist: tqdm ; extra == 'test'
Requires-Dist: notebook ; extra == 'test'
Requires-Dist: folktables ; extra == 'test'
Requires-Dist: hyperparameter-tuning ; extra == 'test'
Requires-Dist: fairlearn ; extra == 'test'
Requires-Dist: lightgbm ; extra == 'test'
Requires-Dist: fairgbm ; extra == 'test'
